{
  "openapi": "3.0.1",
  "info": {
    "title": "EjerciciosORM",
    "version": "1.0"
  },
  "paths": {
    "/api/TodosLosEmpleados": {
      "get": {
        "tags": [
          "Empleados"
        ],
        "responses": {
          "200": {
            "description": "OK",
            "content": {
              "text/plain": {
                "schema": {
                  "type": "array",
                  "items": {
                    "$ref": "#/components/schemas/Empleado"
                  }
                }
              },
              "application/json": {
                "schema": {
                  "type": "array",
                  "items": {
                    "$ref": "#/components/schemas/Empleado"
                  }
                }
              },
              "text/json": {
                "schema": {
                  "type": "array",
                  "items": {
                    "$ref": "#/components/schemas/Empleado"
                  }
                }
              }
            }
          }
        }
      }
    },
    "/api/CantidadEmpleados": {
      "get": {
        "tags": [
          "Empleados"
        ],
        "responses": {
          "200": {
            "description": "OK",
            "content": {
              "text/plain": {
                "schema": {
                  "type": "integer",
                  "format": "int32"
                }
              },
              "application/json": {
                "schema": {
                  "type": "integer",
                  "format": "int32"
                }
              },
              "text/json": {
                "schema": {
                  "type": "integer",
                  "format": "int32"
                }
              }
            }
          }
        }
      }
    },
    "/api/EmpleadoPorID": {
      "get": {
        "tags": [
          "Empleados"
        ],
        "parameters": [
          {
            "name": "empleadoID",
            "in": "query",
            "schema": {
              "type": "integer",
              "format": "int32"
            }
          }
        ],
        "responses": {
          "200": {
            "description": "OK",
            "content": {
              "text/plain": {
                "schema": {
                  "$ref": "#/components/schemas/Empleado"
                }
              },
              "application/json": {
                "schema": {
                  "$ref": "#/components/schemas/Empleado"
                }
              },
              "text/json": {
                "schema": {
                  "$ref": "#/components/schemas/Empleado"
                }
              }
            }
          }
        }
      }
    },
    "/api/EmpleadosPorNombre": {
      "get": {
        "tags": [
          "Empleados"
        ],
        "parameters": [
          {
            "name": "nombreEmpleado",
            "in": "query",
            "schema": {
              "type": "string"
            }
          }
        ],
        "responses": {
          "200": {
            "description": "OK",
            "content": {
              "text/plain": {
                "schema": {
                  "$ref": "#/components/schemas/Empleado"
                }
              },
              "application/json": {
                "schema": {
                  "$ref": "#/components/schemas/Empleado"
                }
              },
              "text/json": {
                "schema": {
                  "$ref": "#/components/schemas/Empleado"
                }
              }
            }
          }
        }
      }
    },
    "/api/EmpleadoPorTitulo": {
      "get": {
        "tags": [
          "Empleados"
        ],
        "parameters": [
          {
            "name": "titulo",
            "in": "query",
            "schema": {
              "type": "string"
            }
          }
        ],
        "responses": {
          "200": {
            "description": "OK",
            "content": {
              "text/plain": {
                "schema": {
                  "$ref": "#/components/schemas/Empleado"
                }
              },
              "application/json": {
                "schema": {
                  "$ref": "#/components/schemas/Empleado"
                }
              },
              "text/json": {
                "schema": {
                  "$ref": "#/components/schemas/Empleado"
                }
              }
            }
          }
        }
      }
    },
    "/api/EmpleadoPorPais": {
      "get": {
        "tags": [
          "Empleados"
        ],
        "parameters": [
          {
            "name": "country",
            "in": "query",
            "schema": {
              "type": "string"
            }
          }
        ],
        "responses": {
          "200": {
            "description": "OK",
            "content": {
              "text/plain": {
                "schema": {
                  "$ref": "#/components/schemas/Empleado"
                }
              },
              "application/json": {
                "schema": {
                  "$ref": "#/components/schemas/Empleado"
                }
              },
              "text/json": {
                "schema": {
                  "$ref": "#/components/schemas/Empleado"
                }
              }
            }
          }
        }
      }
    },
    "/api/TodosLosEmpleadosPorPais": {
      "get": {
        "tags": [
          "Empleados"
        ],
        "parameters": [
          {
            "name": "country",
            "in": "query",
            "schema": {
              "type": "string"
            }
          }
        ],
        "responses": {
          "200": {
            "description": "OK",
            "content": {
              "text/plain": {
                "schema": {
                  "type": "array",
                  "items": {
                    "$ref": "#/components/schemas/Empleado"
                  }
                }
              },
              "application/json": {
                "schema": {
                  "type": "array",
                  "items": {
                    "$ref": "#/components/schemas/Empleado"
                  }
                }
              },
              "text/json": {
                "schema": {
                  "type": "array",
                  "items": {
                    "$ref": "#/components/schemas/Empleado"
                  }
                }
              }
            }
          }
        }
      }
    },
    "/api/ElEmpleadoMasGrande": {
      "get": {
        "tags": [
          "Empleados"
        ],
        "responses": {
          "200": {
            "description": "OK",
            "content": {
              "text/plain": {
                "schema": {
                  "$ref": "#/components/schemas/Empleado"
                }
              },
              "application/json": {
                "schema": {
                  "$ref": "#/components/schemas/Empleado"
                }
              },
              "text/json": {
                "schema": {
                  "$ref": "#/components/schemas/Empleado"
                }
              }
            }
          }
        }
      }
    },
    "/api/CantidadEmpleadosPorTitulos": {
      "get": {
        "tags": [
          "Empleados"
        ],
        "responses": {
          "200": {
            "description": "OK"
          }
        }
      }
    },
    "/api/ObtenerProductosConCategoria": {
      "get": {
        "tags": [
          "Empleados"
        ],
        "responses": {
          "200": {
            "description": "OK",
            "content": {
              "text/plain": {
                "schema": {
                  "type": "array",
                  "items": {
                    "$ref": "#/components/schemas/Producto"
                  }
                }
              },
              "application/json": {
                "schema": {
                  "type": "array",
                  "items": {
                    "$ref": "#/components/schemas/Producto"
                  }
                }
              },
              "text/json": {
                "schema": {
                  "type": "array",
                  "items": {
                    "$ref": "#/components/schemas/Producto"
                  }
                }
              }
            }
          }
        }
      }
    },
    "/api/ObtenerProductosQueContienen": {
      "get": {
        "tags": [
          "Empleados"
        ],
        "parameters": [
          {
            "name": "palabra",
            "in": "query",
            "schema": {
              "type": "string"
            }
          }
        ],
        "responses": {
          "200": {
            "description": "OK",
            "content": {
              "text/plain": {
                "schema": {
                  "type": "array",
                  "items": {
                    "$ref": "#/components/schemas/Producto"
                  }
                }
              },
              "application/json": {
                "schema": {
                  "type": "array",
                  "items": {
                    "$ref": "#/components/schemas/Producto"
                  }
                }
              },
              "text/json": {
                "schema": {
                  "type": "array",
                  "items": {
                    "$ref": "#/components/schemas/Producto"
                  }
                }
              }
            }
          }
        }
      }
    }
  },
  "components": {
    "schemas": {
      "Empleado": {
        "type": "object",
        "properties": {
          "employeeID": {
            "type": "integer",
            "format": "int32"
          },
          "lastName": {
            "type": "string",
            "nullable": true
          },
          "firstName": {
            "type": "string",
            "nullable": true
          },
          "title": {
            "type": "string",
            "nullable": true
          },
          "country": {
            "type": "string",
            "nullable": true
          },
          "city": {
            "type": "string",
            "nullable": true
          },
          "birthDate": {
            "type": "string",
            "format": "date-time"
          },
          "hireDate": {
            "type": "string",
            "format": "date-time"
          }
        },
        "additionalProperties": false
      },
      "Producto": {
        "type": "object",
        "properties": {
          "productName": {
            "type": "string",
            "nullable": true
          },
          "categoryID": {
            "type": "integer",
            "format": "int32"
          },
          "productID": {
            "type": "integer",
            "format": "int32"
          }
        },
        "additionalProperties": false
      }
    }
  }
}